rnotes/__init__.py
rnotes/__main__.py
rnotes/main.py
rnotes/runner.py
rnotes-1.1.4.dist-info/LICENSE
rnotes-1.1.4.dist-info/METADATA
rnotes-1.1.4.dist-info/WHEEL
rnotes-1.1.4.dist-info/entry_points.txt
rnotes-1.1.4.dist-info/top_level.txt
rnotes-1.1.4.dist-info/RECORD
