Metadata-Version: 2.1
Name: rnotes
Version: 1.1.4
Summary: Release notes manager
Home-page: https://github.com/AtakamaLLC/rnotes
License: UNKNOWN
Platform: UNKNOWN
Requires-Dist: pyyaml (==6.*)
